<?xml version='1.0' encoding='windows-1252'?>
<GateDocument version="3">
<!-- The document's features-->

<GateDocumentFeatures>
<Feature>
  <Name className="java.lang.String">gate.SourceURL</Name>
  <Value className="java.lang.String">file:/C:/RCV%20data/rcv1/19960823/10234newsML.xml</Value>
</Feature>
<Feature>
  <Name className="java.lang.String">MimeType</Name>
  <Value className="java.lang.String">text/xml</Value>
</Feature>
</GateDocumentFeatures>
<!-- The document content area with serialized nodes -->

<TextWithNodes><Node id="0"/>
<Node id="1"/>ISRAEL: Netanyahu targets illegal foreign workers.<Node id="51"/>
<Node id="52"/>Netanyahu targets illegal foreign workers.<Node id="94"/>
<Node id="95"/>Jeffrey Heller<Node id="109"/>
<Node id="110"/>JERUSALEM 1996-08-23<Node id="130"/>
<Node id="131"/>
<Node id="132"/>Israel's government on Friday considered for the first time ways to<Node id="199"/> cut a growing dependence<Node id="224"/> on <Node id="228"/>foreign workers<Node id="243"/> who have taken jobs which are off-limits to Palestinians and unwanted by Jews.<Node id="322"/>
<Node id="323"/>"We will act to reduce drastically the presence of illegal foreign workers as well as cut the scope of foreign labourers who enter the country with a permit," a cabinet statement quoted Prime Minister Benjamin Netanyahu as saying<Node id="552"/>.<Node id="553"/>
<Node id="554"/>The communique said the cabinet would take a "practical decision" next week.<Node id="630"/>
<Node id="631"/>"We will<Node id="639"/> propose expelling<Node id="657"/> about<Node id="663"/> 1,000 illegal foreign labourers<Node id="695"/> from Israel a month,"<Node id="717"/> Labour and Welfare Minister Eli Ishai<Node id="755"/> told Israel Radio before Friday's debate.<Node id="797"/>
<Node id="798"/>But Ishai's plan was no blueprint for a mass exodus from Israel of workers from countries such as Romania, Thailand, Turkey and China who now do the low-paying manual labour of Palestinians barred from the Jewish state for security reasons.<Node id="1038"/>
<Node id="1039"/>It would take authorities more than eight years to expel all of the 100,000 foreigners he said were working in Israel without a permit -- assuming police could round all of them up and no new illegal labourers slipped into the country.<Node id="1274"/>
<Node id="1275"/>Ishai said another 100,000 foreigners had valid work papers.<Node id="1335"/>
<Node id="1336"/>"There is a problem here. (Hiring foreigners) pays -- it is good for building contractors....We may have to keep a quota of foreign workers. The question is how many," Ishai said.<Node id="1515"/>
<Node id="1516"/>Many Israelis initially welcomed the blue-collar foreign influx at the height of the six-year-long Palestinian uprising that began in 1987, during the course of which Arab guerrillas knifed Jews in Israeli cities.<Node id="1729"/>
<Node id="1730"/>But while Israeli law required Palestinian workers to return to their homes in the occupied territories each evening, foreigners remain overnight in squalid housing.<Node id="1895"/>
<Node id="1896"/>"Go look at the old central bus station area (in Tel Aviv). It has all the things you see in the Bronx," legislator Ran Cohen told the radio, comparing the foreign workers' slum area to the New York borough known for poverty and crime.<Node id="2131"/>
<Node id="2132"/>Cohen called for the establishment of "transit camps" to hold illegal immigrants for several days before expulsion, a proposal which his left-wing Meretz party colleague Amnon Rubinstein said would hurt Israel's image.<Node id="2350"/>
<Node id="2351"/>"It won't be a concentration camp," Cohen snapped.<Node id="2401"/>
<Node id="2402"/>The cabinet communique quoted Netanyahu as saying that while "strong action" was needed to stop foreign workers staying in Israel illegally, "we are talking about human beings and therefore must treat them accordingly".<Node id="2621"/>
<Node id="2622"/>Israel's Channel Two television showed on Thursday six Turkish workers locked in a shack on an Israeli farm by their employer, apparently over a financial dispute.<Node id="2785"/>
<Node id="2786"/>"It is just like a ghetto," said an incredulous police officer at the scene.<Node id="2862"/>
<Node id="2863"/>Nigerians cleaning apartments, Thais picking flowers in greenhouses, Chinese building workers and Filipina nannies have become permanent fixtures in the Jewish state.<Node id="3029"/>
<Node id="3030"/>The Palestinian Authority has demanded Israel allow more of its people in to work, saying an Israeli closure had crippled the economy in the self-ruled areas.<Node id="3188"/>
<Node id="3189"/>Before the Palestinian uprising, as many as 160,000 Arabs from the West Bank and Gaza worked in Israel.<Node id="3292"/>
<Node id="3293"/>Israel sealed off the territories and stopped Palestinians from entering in February after the first in a series of Moslem suicide bombings that killed 59 people -- including seven Romanian workers. Today some 30,000 Palestinians work in Israel.<Node id="3538"/>
<Node id="3539"/>
<Node id="3540"/>(c) Reuters Limited 1996<Node id="3564"/>
<Node id="3565"/>
<Node id="3566"/>
  <Node id="3569"/>
    <Node id="3574"/>
  <Node id="3577"/>
<Node id="3578"/>
<Node id="3579"/>
  <Node id="3582"/>
    <Node id="3587"/>
  <Node id="3590"/>
  <Node id="3593"/>
    <Node id="3598"/>
  <Node id="3601"/>
  <Node id="3604"/>
    <Node id="3609"/>
  <Node id="3612"/>
  <Node id="3615"/>
    <Node id="3620"/>
  <Node id="3623"/>
  <Node id="3626"/>
    <Node id="3631"/>
  <Node id="3634"/>
<Node id="3635"/>
<Node id="3636"/>
<Node id="3637"/>
<Node id="3638"/>
<Node id="3639"/>
<Node id="3640"/>
<Node id="3641"/>
<Node id="3642"/>
<Node id="3643"/>
<Node id="3644"/></TextWithNodes>
<!-- The default annotation set -->

<AnnotationSet>
<Annotation Id="49" Type="sentence" StartNode="52" EndNode="94">
<Feature>
  <Name className="java.lang.String">intensity</Name>
  <Value className="java.lang.String">medium</Value>
</Feature>
<Feature>
  <Name className="java.lang.String">sentence_id</Name>
  <Value className="java.lang.String">S1</Value>
</Feature>
<Feature>
  <Name className="java.lang.String">subjective/objective</Name>
  <Value className="java.lang.String">objective</Value>
</Feature>
<Feature>
  <Name className="java.lang.String">polarity</Name>
  <Value className="java.lang.String">neutral</Value>
</Feature>
</Annotation>
<Annotation Id="50" Type="source_phrase" StartNode="199" EndNode="224">
<Feature>
  <Name className="java.lang.String">source_phrase_id</Name>
  <Value className="java.lang.String">S2_1</Value>
</Feature>
<Feature>
  <Name className="java.lang.String">sentence_id</Name>
  <Value className="java.lang.String">S2</Value>
</Feature>
<Feature>
  <Name className="java.lang.String">polarity</Name>
  <Value className="java.lang.String">negative</Value>
</Feature>
</Annotation>
<Annotation Id="51" Type="direct_target" StartNode="228" EndNode="243">
<Feature>
  <Name className="java.lang.String">source_phrase_id</Name>
  <Value className="java.lang.String">S2_1</Value>
</Feature>
<Feature>
  <Name className="java.lang.String">direct_target_id</Name>
  <Value className="java.lang.String">DT2_1</Value>
</Feature>
<Feature>
  <Name className="java.lang.String">sentence_id</Name>
  <Value className="java.lang.String">S2</Value>
</Feature>
<Feature>
  <Name className="java.lang.String">polarity</Name>
  <Value className="java.lang.String">negative</Value>
</Feature>
</Annotation>
<Annotation Id="52" Type="sentence" StartNode="132" EndNode="322">
<Feature>
  <Name className="java.lang.String">intensity</Name>
  <Value className="java.lang.String">medium</Value>
</Feature>
<Feature>
  <Name className="java.lang.String">sentence_id</Name>
  <Value className="java.lang.String">S2</Value>
</Feature>
<Feature>
  <Name className="java.lang.String">subjective/objective</Name>
  <Value className="java.lang.String">objective</Value>
</Feature>
<Feature>
  <Name className="java.lang.String">polarity</Name>
  <Value className="java.lang.String">negative</Value>
</Feature>
</Annotation>
<Annotation Id="53" Type="sentence" StartNode="323" EndNode="552">
<Feature>
  <Name className="java.lang.String">intensity</Name>
  <Value className="java.lang.String">medium</Value>
</Feature>
<Feature>
  <Name className="java.lang.String">sentence_id</Name>
  <Value className="java.lang.String">S3</Value>
</Feature>
<Feature>
  <Name className="java.lang.String">subjective/objective</Name>
  <Value className="java.lang.String">subjective</Value>
</Feature>
<Feature>
  <Name className="java.lang.String">polarity</Name>
  <Value className="java.lang.String">negative</Value>
</Feature>
</Annotation>
<Annotation Id="54" Type="sentence" StartNode="554" EndNode="630">
<Feature>
  <Name className="java.lang.String">intensity</Name>
  <Value className="java.lang.String">medium</Value>
</Feature>
<Feature>
  <Name className="java.lang.String">sentence_id</Name>
  <Value className="java.lang.String">S4</Value>
</Feature>
<Feature>
  <Name className="java.lang.String">subjective/objective</Name>
  <Value className="java.lang.String">objective</Value>
</Feature>
<Feature>
  <Name className="java.lang.String">polarity</Name>
  <Value className="java.lang.String">neutral</Value>
</Feature>
</Annotation>
<Annotation Id="55" Type="narrator" StartNode="717" EndNode="755">
<Feature>
  <Name className="java.lang.String">narrator_id</Name>
  <Value className="java.lang.String">N5_1</Value>
</Feature>
<Feature>
  <Name className="java.lang.String">sentence_id</Name>
  <Value className="java.lang.String">S5</Value>
</Feature>
</Annotation>
<Annotation Id="56" Type="source_phrase" StartNode="639" EndNode="657">
<Feature>
  <Name className="java.lang.String">source_phrase_id</Name>
  <Value className="java.lang.String">S5_1</Value>
</Feature>
<Feature>
  <Name className="java.lang.String">sentence_id</Name>
  <Value className="java.lang.String">S5</Value>
</Feature>
<Feature>
  <Name className="java.lang.String">polarity</Name>
  <Value className="java.lang.String">negative</Value>
</Feature>
</Annotation>
<Annotation Id="57" Type="direct_target" StartNode="663" EndNode="695">
<Feature>
  <Name className="java.lang.String">source_phrase_id</Name>
  <Value className="java.lang.String">S5_1</Value>
</Feature>
<Feature>
  <Name className="java.lang.String">direct_target_id</Name>
  <Value className="java.lang.String">DT5_1</Value>
</Feature>
<Feature>
  <Name className="java.lang.String">sentence_id</Name>
  <Value className="java.lang.String">S5</Value>
</Feature>
<Feature>
  <Name className="java.lang.String">polarity</Name>
  <Value className="java.lang.String">negative</Value>
</Feature>
</Annotation>
<Annotation Id="58" Type="sentence" StartNode="631" EndNode="797">
<Feature>
  <Name className="java.lang.String">intensity</Name>
  <Value className="java.lang.String">medium</Value>
</Feature>
<Feature>
  <Name className="java.lang.String">sentence_id</Name>
  <Value className="java.lang.String">S5</Value>
</Feature>
<Feature>
  <Name className="java.lang.String">subjective/objective</Name>
  <Value className="java.lang.String">subjective</Value>
</Feature>
<Feature>
  <Name className="java.lang.String">polarity</Name>
  <Value className="java.lang.String">negative</Value>
</Feature>
</Annotation>
<Annotation Id="59" Type="sentence" StartNode="798" EndNode="1038">
<Feature>
  <Name className="java.lang.String">intensity</Name>
  <Value className="java.lang.String">medium</Value>
</Feature>
<Feature>
  <Name className="java.lang.String">sentence_id</Name>
  <Value className="java.lang.String">S6</Value>
</Feature>
<Feature>
  <Name className="java.lang.String">subjective/objective</Name>
  <Value className="java.lang.String">objective</Value>
</Feature>
<Feature>
  <Name className="java.lang.String">polarity</Name>
  <Value className="java.lang.String">neutral</Value>
</Feature>
</Annotation>
</AnnotationSet>

<!-- Named annotation set -->

<AnnotationSet Name="Original markups">
<Annotation Id="0" Type="newsitem" StartNode="0" EndNode="3644">
<Feature>
  <Name className="java.lang.String">date</Name>
  <Value className="java.lang.String">1996-08-23</Value>
</Feature>
<Feature>
  <Name className="java.lang.String">itemid</Name>
  <Value className="java.lang.String">10234</Value>
</Feature>
<Feature>
  <Name className="java.lang.String">xml:lang</Name>
  <Value className="java.lang.String">en</Value>
</Feature>
<Feature>
  <Name className="java.lang.String">id</Name>
  <Value className="java.lang.String">root</Value>
</Feature>
</Annotation>
<Annotation Id="1" Type="title" StartNode="1" EndNode="51">
</Annotation>
<Annotation Id="2" Type="headline" StartNode="52" EndNode="94">
</Annotation>
<Annotation Id="3" Type="byline" StartNode="95" EndNode="109">
</Annotation>
<Annotation Id="4" Type="dateline" StartNode="110" EndNode="130">
</Annotation>
<Annotation Id="5" Type="text" StartNode="131" EndNode="3539">
</Annotation>
<Annotation Id="6" Type="p" StartNode="132" EndNode="322">
</Annotation>
<Annotation Id="7" Type="p" StartNode="323" EndNode="553">
</Annotation>
<Annotation Id="8" Type="p" StartNode="554" EndNode="630">
</Annotation>
<Annotation Id="9" Type="p" StartNode="631" EndNode="797">
</Annotation>
<Annotation Id="10" Type="p" StartNode="798" EndNode="1038">
</Annotation>
<Annotation Id="11" Type="p" StartNode="1039" EndNode="1274">
</Annotation>
<Annotation Id="12" Type="p" StartNode="1275" EndNode="1335">
</Annotation>
<Annotation Id="13" Type="p" StartNode="1336" EndNode="1515">
</Annotation>
<Annotation Id="14" Type="p" StartNode="1516" EndNode="1729">
</Annotation>
<Annotation Id="15" Type="p" StartNode="1730" EndNode="1895">
</Annotation>
<Annotation Id="16" Type="p" StartNode="1896" EndNode="2131">
</Annotation>
<Annotation Id="17" Type="p" StartNode="2132" EndNode="2350">
</Annotation>
<Annotation Id="18" Type="p" StartNode="2351" EndNode="2401">
</Annotation>
<Annotation Id="19" Type="p" StartNode="2402" EndNode="2621">
</Annotation>
<Annotation Id="20" Type="p" StartNode="2622" EndNode="2785">
</Annotation>
<Annotation Id="21" Type="p" StartNode="2786" EndNode="2862">
</Annotation>
<Annotation Id="22" Type="p" StartNode="2863" EndNode="3029">
</Annotation>
<Annotation Id="23" Type="p" StartNode="3030" EndNode="3188">
</Annotation>
<Annotation Id="24" Type="p" StartNode="3189" EndNode="3292">
</Annotation>
<Annotation Id="25" Type="p" StartNode="3293" EndNode="3538">
</Annotation>
<Annotation Id="26" Type="copyright" StartNode="3540" EndNode="3564">
</Annotation>
<Annotation Id="27" Type="metadata" StartNode="3565" EndNode="3643">
</Annotation>
<Annotation Id="28" Type="codes" StartNode="3566" EndNode="3578">
<Feature>
  <Name className="java.lang.String">class</Name>
  <Value className="java.lang.String">bip:countries:1.0</Value>
</Feature>
</Annotation>
<Annotation Id="29" Type="code" StartNode="3569" EndNode="3577">
<Feature>
  <Name className="java.lang.String">code</Name>
  <Value className="java.lang.String">ISRAEL</Value>
</Feature>
</Annotation>
<Annotation Id="30" Type="editdetail" StartNode="3574" EndNode="3574">
<Feature>
  <Name className="java.lang.String">attribution</Name>
  <Value className="java.lang.String">Reuters BIP Coding Group</Value>
</Feature>
<Feature>
  <Name className="java.lang.String">date</Name>
  <Value className="java.lang.String">1996-08-23</Value>
</Feature>
<Feature>
  <Name className="java.lang.String">action</Name>
  <Value className="java.lang.String">confirmed</Value>
</Feature>
<Feature>
  <Name className="java.lang.String">isEmptyAndSpan</Name>
  <Value className="java.lang.String">true</Value>
</Feature>
</Annotation>
<Annotation Id="31" Type="codes" StartNode="3579" EndNode="3635">
<Feature>
  <Name className="java.lang.String">class</Name>
  <Value className="java.lang.String">bip:topics:1.0</Value>
</Feature>
</Annotation>
<Annotation Id="32" Type="code" StartNode="3582" EndNode="3590">
<Feature>
  <Name className="java.lang.String">code</Name>
  <Value className="java.lang.String">E41</Value>
</Feature>
</Annotation>
<Annotation Id="33" Type="editdetail" StartNode="3587" EndNode="3587">
<Feature>
  <Name className="java.lang.String">attribution</Name>
  <Value className="java.lang.String">Reuters BIP Coding Group</Value>
</Feature>
<Feature>
  <Name className="java.lang.String">date</Name>
  <Value className="java.lang.String">1996-08-23</Value>
</Feature>
<Feature>
  <Name className="java.lang.String">action</Name>
  <Value className="java.lang.String">confirmed</Value>
</Feature>
<Feature>
  <Name className="java.lang.String">isEmptyAndSpan</Name>
  <Value className="java.lang.String">true</Value>
</Feature>
</Annotation>
<Annotation Id="34" Type="code" StartNode="3593" EndNode="3601">
<Feature>
  <Name className="java.lang.String">code</Name>
  <Value className="java.lang.String">ECAT</Value>
</Feature>
</Annotation>
<Annotation Id="35" Type="editdetail" StartNode="3598" EndNode="3598">
<Feature>
  <Name className="java.lang.String">attribution</Name>
  <Value className="java.lang.String">Reuters BIP Coding Group</Value>
</Feature>
<Feature>
  <Name className="java.lang.String">date</Name>
  <Value className="java.lang.String">1996-08-23</Value>
</Feature>
<Feature>
  <Name className="java.lang.String">action</Name>
  <Value className="java.lang.String">confirmed</Value>
</Feature>
<Feature>
  <Name className="java.lang.String">isEmptyAndSpan</Name>
  <Value className="java.lang.String">true</Value>
</Feature>
</Annotation>
<Annotation Id="36" Type="code" StartNode="3604" EndNode="3612">
<Feature>
  <Name className="java.lang.String">code</Name>
  <Value className="java.lang.String">GCAT</Value>
</Feature>
</Annotation>
<Annotation Id="37" Type="editdetail" StartNode="3609" EndNode="3609">
<Feature>
  <Name className="java.lang.String">attribution</Name>
  <Value className="java.lang.String">Reuters BIP Coding Group</Value>
</Feature>
<Feature>
  <Name className="java.lang.String">date</Name>
  <Value className="java.lang.String">1996-08-23</Value>
</Feature>
<Feature>
  <Name className="java.lang.String">action</Name>
  <Value className="java.lang.String">confirmed</Value>
</Feature>
<Feature>
  <Name className="java.lang.String">isEmptyAndSpan</Name>
  <Value className="java.lang.String">true</Value>
</Feature>
</Annotation>
<Annotation Id="38" Type="code" StartNode="3615" EndNode="3623">
<Feature>
  <Name className="java.lang.String">code</Name>
  <Value className="java.lang.String">GJOB</Value>
</Feature>
</Annotation>
<Annotation Id="39" Type="editdetail" StartNode="3620" EndNode="3620">
<Feature>
  <Name className="java.lang.String">attribution</Name>
  <Value className="java.lang.String">Reuters BIP Coding Group</Value>
</Feature>
<Feature>
  <Name className="java.lang.String">date</Name>
  <Value className="java.lang.String">1996-08-23</Value>
</Feature>
<Feature>
  <Name className="java.lang.String">action</Name>
  <Value className="java.lang.String">confirmed</Value>
</Feature>
<Feature>
  <Name className="java.lang.String">isEmptyAndSpan</Name>
  <Value className="java.lang.String">true</Value>
</Feature>
</Annotation>
<Annotation Id="40" Type="code" StartNode="3626" EndNode="3634">
<Feature>
  <Name className="java.lang.String">code</Name>
  <Value className="java.lang.String">GPOL</Value>
</Feature>
</Annotation>
<Annotation Id="41" Type="editdetail" StartNode="3631" EndNode="3631">
<Feature>
  <Name className="java.lang.String">attribution</Name>
  <Value className="java.lang.String">Reuters BIP Coding Group</Value>
</Feature>
<Feature>
  <Name className="java.lang.String">date</Name>
  <Value className="java.lang.String">1996-08-23</Value>
</Feature>
<Feature>
  <Name className="java.lang.String">action</Name>
  <Value className="java.lang.String">confirmed</Value>
</Feature>
<Feature>
  <Name className="java.lang.String">isEmptyAndSpan</Name>
  <Value className="java.lang.String">true</Value>
</Feature>
</Annotation>
<Annotation Id="42" Type="dc" StartNode="3636" EndNode="3636">
<Feature>
  <Name className="java.lang.String">isEmptyAndSpan</Name>
  <Value className="java.lang.String">true</Value>
</Feature>
<Feature>
  <Name className="java.lang.String">value</Name>
  <Value className="java.lang.String">1996-08-23</Value>
</Feature>
<Feature>
  <Name className="java.lang.String">element</Name>
  <Value className="java.lang.String">dc.date.created</Value>
</Feature>
</Annotation>
<Annotation Id="43" Type="dc" StartNode="3637" EndNode="3637">
<Feature>
  <Name className="java.lang.String">isEmptyAndSpan</Name>
  <Value className="java.lang.String">true</Value>
</Feature>
<Feature>
  <Name className="java.lang.String">value</Name>
  <Value className="java.lang.String">Reuters Holdings Plc</Value>
</Feature>
<Feature>
  <Name className="java.lang.String">element</Name>
  <Value className="java.lang.String">dc.publisher</Value>
</Feature>
</Annotation>
<Annotation Id="44" Type="dc" StartNode="3638" EndNode="3638">
<Feature>
  <Name className="java.lang.String">isEmptyAndSpan</Name>
  <Value className="java.lang.String">true</Value>
</Feature>
<Feature>
  <Name className="java.lang.String">value</Name>
  <Value className="java.lang.String">1996-08-23</Value>
</Feature>
<Feature>
  <Name className="java.lang.String">element</Name>
  <Value className="java.lang.String">dc.date.published</Value>
</Feature>
</Annotation>
<Annotation Id="45" Type="dc" StartNode="3639" EndNode="3639">
<Feature>
  <Name className="java.lang.String">isEmptyAndSpan</Name>
  <Value className="java.lang.String">true</Value>
</Feature>
<Feature>
  <Name className="java.lang.String">value</Name>
  <Value className="java.lang.String">Reuters</Value>
</Feature>
<Feature>
  <Name className="java.lang.String">element</Name>
  <Value className="java.lang.String">dc.source</Value>
</Feature>
</Annotation>
<Annotation Id="46" Type="dc" StartNode="3640" EndNode="3640">
<Feature>
  <Name className="java.lang.String">isEmptyAndSpan</Name>
  <Value className="java.lang.String">true</Value>
</Feature>
<Feature>
  <Name className="java.lang.String">value</Name>
  <Value className="java.lang.String">JERUSALEM</Value>
</Feature>
<Feature>
  <Name className="java.lang.String">element</Name>
  <Value className="java.lang.String">dc.creator.location</Value>
</Feature>
</Annotation>
<Annotation Id="47" Type="dc" StartNode="3641" EndNode="3641">
<Feature>
  <Name className="java.lang.String">isEmptyAndSpan</Name>
  <Value className="java.lang.String">true</Value>
</Feature>
<Feature>
  <Name className="java.lang.String">value</Name>
  <Value className="java.lang.String">ISRAEL</Value>
</Feature>
<Feature>
  <Name className="java.lang.String">element</Name>
  <Value className="java.lang.String">dc.creator.location.country.name</Value>
</Feature>
</Annotation>
<Annotation Id="48" Type="dc" StartNode="3642" EndNode="3642">
<Feature>
  <Name className="java.lang.String">isEmptyAndSpan</Name>
  <Value className="java.lang.String">true</Value>
</Feature>
<Feature>
  <Name className="java.lang.String">value</Name>
  <Value className="java.lang.String">Reuters</Value>
</Feature>
<Feature>
  <Name className="java.lang.String">element</Name>
  <Value className="java.lang.String">dc.source</Value>
</Feature>
</Annotation>
</AnnotationSet>

</GateDocument>
