<?xml version='1.0' encoding='windows-1252'?>
<GateDocument version="3">
<!-- The document's features-->

<GateDocumentFeatures>
<Feature>
  <Name className="java.lang.String">gate.SourceURL</Name>
  <Value className="java.lang.String">file:/C:/RCV%20data/rcv1/19960825/12869newsML.xml</Value>
</Feature>
<Feature>
  <Name className="java.lang.String">MimeType</Name>
  <Value className="java.lang.String">text/xml</Value>
</Feature>
</GateDocumentFeatures>
<!-- The document content area with serialized nodes -->

<TextWithNodes><Node id="0"/>
<Node id="1"/>USA: Brando's "Island of Dr. Moreau" opens at top of box office.<Node id="65"/>
<Node id="66"/>Brando's "Island of Dr. Moreau"<Node id="97"/> <Node id="98"/>opens at top of box office<Node id="124"/>.<Node id="125"/>
<Node id="126"/>Dean Goodman<Node id="138"/>
<Node id="139"/>LOS ANGELES 1996-08-25<Node id="161"/>
<Node id="162"/>
<Node id="163"/>"<Node id="164"/>The Island of Dr. Moreau<Node id="188"/>"<Node id="189"/> overcame some of the worst reviews of the year<Node id="236"/> to <Node id="240"/>open at the top of the U.S. box office<Node id="278"/> with an estimated gross of $9.0 million at the weekend.<Node id="334"/>
<Node id="335"/>Marlon Brando and Val Kilmer star in the third big-screen adaptation of the H.G. Wells science-fiction novel, a <Node id="447"/>troubled project<Node id="463"/> that saw the firing of one director and the departure of one of the stars<Node id="537"/>. <Node id="539"/>The movie is released by New Line Cinema, a unit of Ted Turner's Turner Broadcasting System Inc.<Node id="635"/>
<Node id="636"/>Slipping to second place for the Friday to Sunday period was "Tin Cup" with $8.8 million, according to Exhibitor Relations Co.<Node id="762"/> <Node id="763"/>The<Node id="766"/> Kevin Costner golfing comedy<Node id="795"/> <Node id="796"/>dipped just 13 percent<Node id="818"/> from last weekend and has a 10-day gross of $23.9 million.<Node id="877"/>
<Node id="878"/>Opening in third with $7.4 million was "A Very Brady Sequel", the second movie based on the Brady Bunch television series. The courtroom drama "A Time To Kill" was fourth with $6.2 million followed by Robin Williams' "Jack" with $5.9 million.<Node id="1120"/>
<Node id="1121"/>The movie that earned the most per screen was "She's The One", which opened in 10th with $2.2 million. The romantic comedy, which Ed Burns wrote, directed and starred in, averaged $4,793 per screen, the highest tally in the top-10.<Node id="1352"/>
<Node id="1353"/>"Moreau" followed with a per-screen average of $4,423. According to a Variety magazine poll of critics in New York, Los Angeles, Chicago and Washington D.C., only two liked "Moreau", while 17 did not and 13 were mixed. The Los Angeles Times said it was "disastrous," while Variety said it was "an embarrassment for all concerned."<Node id="1683"/>
<Node id="1684"/>Mitch Goldman, New Line's marketing and distribution president, said the studio "didn't necessarily expect it to be No. 1 this weekend."<Node id="1820"/>
<Node id="1821"/>The PG-13 movie played to predominantly younger audiences, and New Line is going to fine-tune the marketing to appeal to adults by emphasising the science-fiction nature over the horror. Goldman said Brando planned to appear on Larry King's CNN talk show this week to drum up support for the movie.<Node id="2119"/>
<Node id="2120"/>"I think he feels that the critics were unjustifiably cruel, and I think he would like to help people get over them (the critics) and see this movie," Goldman said.<Node id="2284"/>
<Node id="2285"/>Brando, who hasn't had a box office hit since the 1970s, told Variety gossip writer Army Archerd last December the movie "could make $500 million."<Node id="2432"/>
<Node id="2433"/>John Frankenheimer directed "Moreau", replacing Richard Stanley who reportedly had differences with Kilmer. After his departure, actor Rob Morrow left and was replaced by David Thewlis.<Node id="2618"/>
<Node id="2619"/>The Brady movie averaged a disappointing $3,447 per screen despite warm reviews. The first instalment opened at the top of the box office with a four-day total of $14.82 million (average $8,138) during the President's Day holiday in February 1995.<Node id="2866"/>
<Node id="2867"/>At least it outperformed many other movies. "Carpool", a comedy directed by Arthur Hiller, the president of the Academy of Motion Picture Arts and Sciences, opened in 13th with $1.8 million. "John Carpenter's Escape From L.A." fell out of the top 10 in its third weekend, and "Bordello of Blood" fell out in its second.<Node id="3186"/>
<Node id="3187"/>
<Node id="3188"/>(c) Reuters Limited 1996<Node id="3212"/>
<Node id="3213"/>
<Node id="3214"/>
  <Node id="3217"/>
    <Node id="3222"/>
  <Node id="3225"/>
<Node id="3226"/>
<Node id="3227"/>
  <Node id="3230"/>
    <Node id="3235"/>
  <Node id="3238"/>
  <Node id="3241"/>
    <Node id="3246"/>
  <Node id="3249"/>
<Node id="3250"/>
<Node id="3251"/>
  <Node id="3254"/>
    <Node id="3259"/>
  <Node id="3262"/>
  <Node id="3265"/>
    <Node id="3270"/>
  <Node id="3273"/>
  <Node id="3276"/>
    <Node id="3281"/>
  <Node id="3284"/>
  <Node id="3287"/>
    <Node id="3292"/>
  <Node id="3295"/>
<Node id="3296"/>
<Node id="3297"/>
<Node id="3298"/>
<Node id="3299"/>
<Node id="3300"/>
<Node id="3301"/>
<Node id="3302"/>
<Node id="3303"/>
<Node id="3304"/>
<Node id="3305"/></TextWithNodes>
<!-- The default annotation set -->

<AnnotationSet>
<Annotation Id="45" Type="sentence" StartNode="66" EndNode="125">
<Feature>
  <Name className="java.lang.String">intensity</Name>
  <Value className="java.lang.String">high</Value>
</Feature>
<Feature>
  <Name className="java.lang.String">sentence_id</Name>
  <Value className="java.lang.String">S1</Value>
</Feature>
<Feature>
  <Name className="java.lang.String">subjective/objective</Name>
  <Value className="java.lang.String">objective</Value>
</Feature>
<Feature>
  <Name className="java.lang.String">polarity</Name>
  <Value className="java.lang.String">positive</Value>
</Feature>
</Annotation>
<Annotation Id="46" Type="source_phrase" StartNode="98" EndNode="124">
<Feature>
  <Name className="java.lang.String">source_phrase_id</Name>
  <Value className="java.lang.String">S1_1</Value>
</Feature>
<Feature>
  <Name className="java.lang.String">sentence_id</Name>
  <Value className="java.lang.String">S1</Value>
</Feature>
<Feature>
  <Name className="java.lang.String">polarity</Name>
  <Value className="java.lang.String">positive</Value>
</Feature>
</Annotation>
<Annotation Id="47" Type="direct_target" StartNode="66" EndNode="97">
<Feature>
  <Name className="java.lang.String">source_phrase_id</Name>
  <Value className="java.lang.String">S1_1</Value>
</Feature>
<Feature>
  <Name className="java.lang.String">direct_target_id</Name>
  <Value className="java.lang.String">DT1_1</Value>
</Feature>
<Feature>
  <Name className="java.lang.String">sentence_id</Name>
  <Value className="java.lang.String">S1</Value>
</Feature>
</Annotation>
<Annotation Id="49" Type="source_phrase" StartNode="189" EndNode="236">
<Feature>
  <Name className="java.lang.String">source_phrase_id</Name>
  <Value className="java.lang.String">S2_1</Value>
</Feature>
<Feature>
  <Name className="java.lang.String">sentence_id</Name>
  <Value className="java.lang.String">S2</Value>
</Feature>
<Feature>
  <Name className="java.lang.String">polarity</Name>
  <Value className="java.lang.String">positive</Value>
</Feature>
</Annotation>
<Annotation Id="50" Type="source_phrase" StartNode="240" EndNode="278">
<Feature>
  <Name className="java.lang.String">source_phrase_id</Name>
  <Value className="java.lang.String">S2_2</Value>
</Feature>
<Feature>
  <Name className="java.lang.String">sentence_id</Name>
  <Value className="java.lang.String">S2</Value>
</Feature>
<Feature>
  <Name className="java.lang.String">polarity</Name>
  <Value className="java.lang.String">positive</Value>
</Feature>
</Annotation>
<Annotation Id="51" Type="direct_target" StartNode="164" EndNode="188">
<Feature>
  <Name className="java.lang.String">source_phrase_id</Name>
  <Value className="java.lang.String">S2_1,S2_2</Value>
</Feature>
<Feature>
  <Name className="java.lang.String">direct_target_id</Name>
  <Value className="java.lang.String">DT2_1</Value>
</Feature>
<Feature>
  <Name className="java.lang.String">sentence_id</Name>
  <Value className="java.lang.String">S2</Value>
</Feature>
</Annotation>
<Annotation Id="52" Type="sentence" StartNode="163" EndNode="334">
<Feature>
  <Name className="java.lang.String">intensity</Name>
  <Value className="java.lang.String">medium</Value>
</Feature>
<Feature>
  <Name className="java.lang.String">sentence_id</Name>
  <Value className="java.lang.String">S2</Value>
</Feature>
<Feature>
  <Name className="java.lang.String">subjective/objective</Name>
  <Value className="java.lang.String">objective</Value>
</Feature>
<Feature>
  <Name className="java.lang.String">polarity</Name>
  <Value className="java.lang.String">positive</Value>
</Feature>
</Annotation>
<Annotation Id="53" Type="source_phrase" StartNode="447" EndNode="463">
<Feature>
  <Name className="java.lang.String">source_phrase_id</Name>
  <Value className="java.lang.String">S3_1</Value>
</Feature>
<Feature>
  <Name className="java.lang.String">sentence_id</Name>
  <Value className="java.lang.String">S3</Value>
</Feature>
<Feature>
  <Name className="java.lang.String">polarity</Name>
  <Value className="java.lang.String">negative</Value>
</Feature>
</Annotation>
<Annotation Id="54" Type="sentence" StartNode="335" EndNode="537">
<Feature>
  <Name className="java.lang.String">intensity</Name>
  <Value className="java.lang.String">medium</Value>
</Feature>
<Feature>
  <Name className="java.lang.String">sentence_id</Name>
  <Value className="java.lang.String">S3</Value>
</Feature>
<Feature>
  <Name className="java.lang.String">subjective/objective</Name>
  <Value className="java.lang.String">objective</Value>
</Feature>
<Feature>
  <Name className="java.lang.String">polarity</Name>
  <Value className="java.lang.String">neutral</Value>
</Feature>
</Annotation>
<Annotation Id="55" Type="sentence" StartNode="539" EndNode="635">
<Feature>
  <Name className="java.lang.String">intensity</Name>
  <Value className="java.lang.String">medium</Value>
</Feature>
<Feature>
  <Name className="java.lang.String">sentence_id</Name>
  <Value className="java.lang.String">S4</Value>
</Feature>
<Feature>
  <Name className="java.lang.String">subjective/objective</Name>
  <Value className="java.lang.String">objective</Value>
</Feature>
<Feature>
  <Name className="java.lang.String">polarity</Name>
  <Value className="java.lang.String">neutral</Value>
</Feature>
</Annotation>
<Annotation Id="56" Type="sentence" StartNode="636" EndNode="762">
<Feature>
  <Name className="java.lang.String">intensity</Name>
  <Value className="java.lang.String">medium</Value>
</Feature>
<Feature>
  <Name className="java.lang.String">sentence_id</Name>
  <Value className="java.lang.String">S5</Value>
</Feature>
<Feature>
  <Name className="java.lang.String">subjective/objective</Name>
  <Value className="java.lang.String">objective</Value>
</Feature>
<Feature>
  <Name className="java.lang.String">polarity</Name>
  <Value className="java.lang.String">neutral</Value>
</Feature>
</Annotation>
<Annotation Id="58" Type="source_phrase" StartNode="796" EndNode="818">
<Feature>
  <Name className="java.lang.String">source_phrase_id</Name>
  <Value className="java.lang.String">S6_1</Value>
</Feature>
<Feature>
  <Name className="java.lang.String">sentence_id</Name>
  <Value className="java.lang.String">S6</Value>
</Feature>
<Feature>
  <Name className="java.lang.String">polarity</Name>
  <Value className="java.lang.String">negative</Value>
</Feature>
</Annotation>
<Annotation Id="59" Type="direct_target" StartNode="766" EndNode="795">
<Feature>
  <Name className="java.lang.String">source_phrase_id</Name>
  <Value className="java.lang.String">S6_1</Value>
</Feature>
<Feature>
  <Name className="java.lang.String">direct_target_id</Name>
  <Value className="java.lang.String">DT6_1</Value>
</Feature>
<Feature>
  <Name className="java.lang.String">sentence_id</Name>
  <Value className="java.lang.String">S6</Value>
</Feature>
</Annotation>
<Annotation Id="60" Type="sentence" StartNode="763" EndNode="877">
<Feature>
  <Name className="java.lang.String">intensity</Name>
  <Value className="java.lang.String">medium</Value>
</Feature>
<Feature>
  <Name className="java.lang.String">sentence_id</Name>
  <Value className="java.lang.String">S6</Value>
</Feature>
<Feature>
  <Name className="java.lang.String">subjective/objective</Name>
  <Value className="java.lang.String">objective</Value>
</Feature>
<Feature>
  <Name className="java.lang.String">polarity</Name>
  <Value className="java.lang.String">negative</Value>
</Feature>
</Annotation>
</AnnotationSet>

<!-- Named annotation set -->

<AnnotationSet Name="Original markups">
<Annotation Id="0" Type="newsitem" StartNode="0" EndNode="3305">
<Feature>
  <Name className="java.lang.String">date</Name>
  <Value className="java.lang.String">1996-08-25</Value>
</Feature>
<Feature>
  <Name className="java.lang.String">itemid</Name>
  <Value className="java.lang.String">12869</Value>
</Feature>
<Feature>
  <Name className="java.lang.String">xml:lang</Name>
  <Value className="java.lang.String">en</Value>
</Feature>
<Feature>
  <Name className="java.lang.String">id</Name>
  <Value className="java.lang.String">root</Value>
</Feature>
</Annotation>
<Annotation Id="1" Type="title" StartNode="1" EndNode="65">
</Annotation>
<Annotation Id="2" Type="headline" StartNode="66" EndNode="125">
</Annotation>
<Annotation Id="3" Type="byline" StartNode="126" EndNode="138">
</Annotation>
<Annotation Id="4" Type="dateline" StartNode="139" EndNode="161">
</Annotation>
<Annotation Id="5" Type="text" StartNode="162" EndNode="3187">
</Annotation>
<Annotation Id="6" Type="p" StartNode="163" EndNode="334">
</Annotation>
<Annotation Id="7" Type="p" StartNode="335" EndNode="635">
</Annotation>
<Annotation Id="8" Type="p" StartNode="636" EndNode="877">
</Annotation>
<Annotation Id="9" Type="p" StartNode="878" EndNode="1120">
</Annotation>
<Annotation Id="10" Type="p" StartNode="1121" EndNode="1352">
</Annotation>
<Annotation Id="11" Type="p" StartNode="1353" EndNode="1683">
</Annotation>
<Annotation Id="12" Type="p" StartNode="1684" EndNode="1820">
</Annotation>
<Annotation Id="13" Type="p" StartNode="1821" EndNode="2119">
</Annotation>
<Annotation Id="14" Type="p" StartNode="2120" EndNode="2284">
</Annotation>
<Annotation Id="15" Type="p" StartNode="2285" EndNode="2432">
</Annotation>
<Annotation Id="16" Type="p" StartNode="2433" EndNode="2618">
</Annotation>
<Annotation Id="17" Type="p" StartNode="2619" EndNode="2866">
</Annotation>
<Annotation Id="18" Type="p" StartNode="2867" EndNode="3186">
</Annotation>
<Annotation Id="19" Type="copyright" StartNode="3188" EndNode="3212">
</Annotation>
<Annotation Id="20" Type="metadata" StartNode="3213" EndNode="3304">
</Annotation>
<Annotation Id="21" Type="codes" StartNode="3214" EndNode="3226">
<Feature>
  <Name className="java.lang.String">class</Name>
  <Value className="java.lang.String">bip:countries:1.0</Value>
</Feature>
</Annotation>
<Annotation Id="22" Type="code" StartNode="3217" EndNode="3225">
<Feature>
  <Name className="java.lang.String">code</Name>
  <Value className="java.lang.String">USA</Value>
</Feature>
</Annotation>
<Annotation Id="23" Type="editdetail" StartNode="3222" EndNode="3222">
<Feature>
  <Name className="java.lang.String">attribution</Name>
  <Value className="java.lang.String">Reuters BIP Coding Group</Value>
</Feature>
<Feature>
  <Name className="java.lang.String">date</Name>
  <Value className="java.lang.String">1996-08-25</Value>
</Feature>
<Feature>
  <Name className="java.lang.String">action</Name>
  <Value className="java.lang.String">confirmed</Value>
</Feature>
<Feature>
  <Name className="java.lang.String">isEmptyAndSpan</Name>
  <Value className="java.lang.String">true</Value>
</Feature>
</Annotation>
<Annotation Id="24" Type="codes" StartNode="3227" EndNode="3250">
<Feature>
  <Name className="java.lang.String">class</Name>
  <Value className="java.lang.String">bip:industries:1.0</Value>
</Feature>
</Annotation>
<Annotation Id="25" Type="code" StartNode="3230" EndNode="3238">
<Feature>
  <Name className="java.lang.String">code</Name>
  <Value className="java.lang.String">I97100</Value>
</Feature>
</Annotation>
<Annotation Id="26" Type="editdetail" StartNode="3235" EndNode="3235">
<Feature>
  <Name className="java.lang.String">attribution</Name>
  <Value className="java.lang.String">Reuters BIP Coding Group</Value>
</Feature>
<Feature>
  <Name className="java.lang.String">date</Name>
  <Value className="java.lang.String">1996-08-25</Value>
</Feature>
<Feature>
  <Name className="java.lang.String">action</Name>
  <Value className="java.lang.String">confirmed</Value>
</Feature>
<Feature>
  <Name className="java.lang.String">isEmptyAndSpan</Name>
  <Value className="java.lang.String">true</Value>
</Feature>
</Annotation>
<Annotation Id="27" Type="code" StartNode="3241" EndNode="3249">
<Feature>
  <Name className="java.lang.String">code</Name>
  <Value className="java.lang.String">I97400</Value>
</Feature>
</Annotation>
<Annotation Id="28" Type="editdetail" StartNode="3246" EndNode="3246">
<Feature>
  <Name className="java.lang.String">attribution</Name>
  <Value className="java.lang.String">Reuters BIP Coding Group</Value>
</Feature>
<Feature>
  <Name className="java.lang.String">date</Name>
  <Value className="java.lang.String">1996-08-25</Value>
</Feature>
<Feature>
  <Name className="java.lang.String">action</Name>
  <Value className="java.lang.String">confirmed</Value>
</Feature>
<Feature>
  <Name className="java.lang.String">isEmptyAndSpan</Name>
  <Value className="java.lang.String">true</Value>
</Feature>
</Annotation>
<Annotation Id="29" Type="codes" StartNode="3251" EndNode="3296">
<Feature>
  <Name className="java.lang.String">class</Name>
  <Value className="java.lang.String">bip:topics:1.0</Value>
</Feature>
</Annotation>
<Annotation Id="30" Type="code" StartNode="3254" EndNode="3262">
<Feature>
  <Name className="java.lang.String">code</Name>
  <Value className="java.lang.String">C31</Value>
</Feature>
</Annotation>
<Annotation Id="31" Type="editdetail" StartNode="3259" EndNode="3259">
<Feature>
  <Name className="java.lang.String">attribution</Name>
  <Value className="java.lang.String">Reuters BIP Coding Group</Value>
</Feature>
<Feature>
  <Name className="java.lang.String">date</Name>
  <Value className="java.lang.String">1996-08-25</Value>
</Feature>
<Feature>
  <Name className="java.lang.String">action</Name>
  <Value className="java.lang.String">confirmed</Value>
</Feature>
<Feature>
  <Name className="java.lang.String">isEmptyAndSpan</Name>
  <Value className="java.lang.String">true</Value>
</Feature>
</Annotation>
<Annotation Id="32" Type="code" StartNode="3265" EndNode="3273">
<Feature>
  <Name className="java.lang.String">code</Name>
  <Value className="java.lang.String">CCAT</Value>
</Feature>
</Annotation>
<Annotation Id="33" Type="editdetail" StartNode="3270" EndNode="3270">
<Feature>
  <Name className="java.lang.String">attribution</Name>
  <Value className="java.lang.String">Reuters BIP Coding Group</Value>
</Feature>
<Feature>
  <Name className="java.lang.String">date</Name>
  <Value className="java.lang.String">1996-08-25</Value>
</Feature>
<Feature>
  <Name className="java.lang.String">action</Name>
  <Value className="java.lang.String">confirmed</Value>
</Feature>
<Feature>
  <Name className="java.lang.String">isEmptyAndSpan</Name>
  <Value className="java.lang.String">true</Value>
</Feature>
</Annotation>
<Annotation Id="34" Type="code" StartNode="3276" EndNode="3284">
<Feature>
  <Name className="java.lang.String">code</Name>
  <Value className="java.lang.String">GCAT</Value>
</Feature>
</Annotation>
<Annotation Id="35" Type="editdetail" StartNode="3281" EndNode="3281">
<Feature>
  <Name className="java.lang.String">attribution</Name>
  <Value className="java.lang.String">Reuters BIP Coding Group</Value>
</Feature>
<Feature>
  <Name className="java.lang.String">date</Name>
  <Value className="java.lang.String">1996-08-25</Value>
</Feature>
<Feature>
  <Name className="java.lang.String">action</Name>
  <Value className="java.lang.String">confirmed</Value>
</Feature>
<Feature>
  <Name className="java.lang.String">isEmptyAndSpan</Name>
  <Value className="java.lang.String">true</Value>
</Feature>
</Annotation>
<Annotation Id="36" Type="code" StartNode="3287" EndNode="3295">
<Feature>
  <Name className="java.lang.String">code</Name>
  <Value className="java.lang.String">GENT</Value>
</Feature>
</Annotation>
<Annotation Id="37" Type="editdetail" StartNode="3292" EndNode="3292">
<Feature>
  <Name className="java.lang.String">attribution</Name>
  <Value className="java.lang.String">Reuters BIP Coding Group</Value>
</Feature>
<Feature>
  <Name className="java.lang.String">date</Name>
  <Value className="java.lang.String">1996-08-25</Value>
</Feature>
<Feature>
  <Name className="java.lang.String">action</Name>
  <Value className="java.lang.String">confirmed</Value>
</Feature>
<Feature>
  <Name className="java.lang.String">isEmptyAndSpan</Name>
  <Value className="java.lang.String">true</Value>
</Feature>
</Annotation>
<Annotation Id="38" Type="dc" StartNode="3297" EndNode="3297">
<Feature>
  <Name className="java.lang.String">isEmptyAndSpan</Name>
  <Value className="java.lang.String">true</Value>
</Feature>
<Feature>
  <Name className="java.lang.String">value</Name>
  <Value className="java.lang.String">1996-08-25</Value>
</Feature>
<Feature>
  <Name className="java.lang.String">element</Name>
  <Value className="java.lang.String">dc.date.created</Value>
</Feature>
</Annotation>
<Annotation Id="39" Type="dc" StartNode="3298" EndNode="3298">
<Feature>
  <Name className="java.lang.String">isEmptyAndSpan</Name>
  <Value className="java.lang.String">true</Value>
</Feature>
<Feature>
  <Name className="java.lang.String">value</Name>
  <Value className="java.lang.String">Reuters Holdings Plc</Value>
</Feature>
<Feature>
  <Name className="java.lang.String">element</Name>
  <Value className="java.lang.String">dc.publisher</Value>
</Feature>
</Annotation>
<Annotation Id="40" Type="dc" StartNode="3299" EndNode="3299">
<Feature>
  <Name className="java.lang.String">isEmptyAndSpan</Name>
  <Value className="java.lang.String">true</Value>
</Feature>
<Feature>
  <Name className="java.lang.String">value</Name>
  <Value className="java.lang.String">1996-08-25</Value>
</Feature>
<Feature>
  <Name className="java.lang.String">element</Name>
  <Value className="java.lang.String">dc.date.published</Value>
</Feature>
</Annotation>
<Annotation Id="41" Type="dc" StartNode="3300" EndNode="3300">
<Feature>
  <Name className="java.lang.String">isEmptyAndSpan</Name>
  <Value className="java.lang.String">true</Value>
</Feature>
<Feature>
  <Name className="java.lang.String">value</Name>
  <Value className="java.lang.String">Reuters</Value>
</Feature>
<Feature>
  <Name className="java.lang.String">element</Name>
  <Value className="java.lang.String">dc.source</Value>
</Feature>
</Annotation>
<Annotation Id="42" Type="dc" StartNode="3301" EndNode="3301">
<Feature>
  <Name className="java.lang.String">isEmptyAndSpan</Name>
  <Value className="java.lang.String">true</Value>
</Feature>
<Feature>
  <Name className="java.lang.String">value</Name>
  <Value className="java.lang.String">LOS ANGELES</Value>
</Feature>
<Feature>
  <Name className="java.lang.String">element</Name>
  <Value className="java.lang.String">dc.creator.location</Value>
</Feature>
</Annotation>
<Annotation Id="43" Type="dc" StartNode="3302" EndNode="3302">
<Feature>
  <Name className="java.lang.String">isEmptyAndSpan</Name>
  <Value className="java.lang.String">true</Value>
</Feature>
<Feature>
  <Name className="java.lang.String">value</Name>
  <Value className="java.lang.String">USA</Value>
</Feature>
<Feature>
  <Name className="java.lang.String">element</Name>
  <Value className="java.lang.String">dc.creator.location.country.name</Value>
</Feature>
</Annotation>
<Annotation Id="44" Type="dc" StartNode="3303" EndNode="3303">
<Feature>
  <Name className="java.lang.String">isEmptyAndSpan</Name>
  <Value className="java.lang.String">true</Value>
</Feature>
<Feature>
  <Name className="java.lang.String">value</Name>
  <Value className="java.lang.String">Reuters</Value>
</Feature>
<Feature>
  <Name className="java.lang.String">element</Name>
  <Value className="java.lang.String">dc.source</Value>
</Feature>
</Annotation>
</AnnotationSet>

</GateDocument>
