<?xml version='1.0' encoding='windows-1252'?>
<GateDocument version="3">
<!-- The document's features-->

<GateDocumentFeatures>
<Feature>
  <Name className="java.lang.String">gate.SourceURL</Name>
  <Value className="java.lang.String">file:/C:/RCV%20data/rcv1/19960825/12872newsML.xml</Value>
</Feature>
<Feature>
  <Name className="java.lang.String">MimeType</Name>
  <Value className="java.lang.String">text/xml</Value>
</Feature>
</GateDocumentFeatures>
<!-- The document content area with serialized nodes -->

<TextWithNodes><Node id="0"/>
<Node id="1"/>UK: Bass buys Allied's Carlsberg-Tetley.<Node id="41"/>
<Node id="42"/>Bass buys Allied's Carlsberg-Tetley<Node id="77"/>.<Node id="78"/>
<Node id="79"/>LONDON 1996-08-25<Node id="96"/>
<Node id="97"/>
<Node id="98"/>Bass Plc<Node id="106"/> said on Sunday that it has bought Allied Domecq Plc's interests in Carlsberg-Tetley for 200 million stg in cash.<Node id="219"/>
<Node id="220"/>It said the purchase includes Allied Domecq's 50 percent share of Carslberg-Tetley as well as their beer brands.<Node id="332"/>
<Node id="333"/>Bass added that it has agreed with Carslberg A/S to merge Carlsberg-Tetley and Bass Brewers, conditional on regulatory approval.<Node id="461"/>  <Node id="463"/>
<Node id="464"/>Assuming the merger is completed, Bass expects within three years to achieve annual cost savings of 90 million stg, with additional one-off cash costs of 75 million stg.<Node id="633"/>
<Node id="634"/>The<Node id="637"/> brewer<Node id="644"/> said the transaction should be earnings enhancing before exceptional charges in the year to end September 1997.<Node id="756"/>  <Node id="758"/>
<Node id="759"/>"I am delighted we have been able to agree this merger," said Bass chairman Sir Ian Prosser in a statement.<Node id="866"/>
<Node id="867"/>"This transaction provides Bass with the opportunity to respond positively to market trends by increasing our own competitiveness, both at home and overseas," said Prosser.<Node id="1039"/>
<Node id="1040"/>"Brewers continue to face a whole range of competitive pressures on wholesale volumes, prices and margins, and it is these pressures that are forcing consolidation," he said.  <Node id="1216"/>
<Node id="1217"/>Carlsberg will contribute its interests in Carlsberg-Tetley and 20 million stg in cash in exchange for a 20 percent share of the combined Bass Brewers and Carlsberg-Tetley business.<Node id="1398"/>
<Node id="1399"/>Bass will receive 50 percent of all profits earned by Carlsberg-Tetley until the merger is complete. If regulatory approval cannot be obtained, Bass has the option to put onto Carlsberg for 110 million stg all of the stake acquired from Allied Domecq, which would reimburse Bass 30 million stg.<Node id="1693"/>
<Node id="1694"/>Carlsberg-Tetley made an operating profit of 52 million stg in the year ending August 19 1995 and had net assets of 637 million stg.  <Node id="1828"/>
<Node id="1829"/>Bass Brewers' operating profit for the year to end September 1995 was 113 million stg. It had net assets of 890 million stg.<Node id="1953"/>
<Node id="1954"/>Its expected share of the UK beer market following the merger will be around 35 percent. It plans to continue operating all breweries in the enlarged busines, except Warrington, the closure of which has already been announced by Carlsberg-Tetley. "The merger will enable us to realise singinificant benefits in production, distribution and marketing, and to respond even more effectively to evolving customer demands," said Prosser.<Node id="2386"/>
<Node id="2387"/>"The higher levels of efficiency and competitiveness that we will be able to achieve also offer the best safeguard for the long-term future of UK jobs, brands and breweries," he said.<Node id="2570"/>
<Node id="2571"/>-- London Newsroom, +44 171 542 7717<Node id="2607"/>
<Node id="2608"/>
<Node id="2609"/>(c) Reuters Limited 1996<Node id="2633"/>
<Node id="2634"/>
<Node id="2635"/>
  <Node id="2638"/>
    <Node id="2643"/>
  <Node id="2646"/>
<Node id="2647"/>
<Node id="2648"/>
  <Node id="2651"/>
    <Node id="2656"/>
  <Node id="2659"/>
<Node id="2660"/>
<Node id="2661"/>
<Node id="2662"/>
<Node id="2663"/>
<Node id="2664"/>
<Node id="2665"/>
<Node id="2666"/>
<Node id="2667"/>
<Node id="2668"/>
<Node id="2669"/></TextWithNodes>
<!-- The default annotation set -->

<AnnotationSet>
<Annotation Id="35" Type="sentence" StartNode="42" EndNode="77">
<Feature>
  <Name className="java.lang.String">intensity</Name>
  <Value className="java.lang.String">medium</Value>
</Feature>
<Feature>
  <Name className="java.lang.String">sentence_id</Name>
  <Value className="java.lang.String">S1</Value>
</Feature>
<Feature>
  <Name className="java.lang.String">subjective/objective</Name>
  <Value className="java.lang.String">objective</Value>
</Feature>
<Feature>
  <Name className="java.lang.String">polarity</Name>
  <Value className="java.lang.String">neutral</Value>
</Feature>
</Annotation>
<Annotation Id="36" Type="narrator" StartNode="98" EndNode="106">
<Feature>
  <Name className="java.lang.String">narrator_id</Name>
  <Value className="java.lang.String">N2_1</Value>
</Feature>
<Feature>
  <Name className="java.lang.String">sentence_id</Name>
  <Value className="java.lang.String">S2</Value>
</Feature>
</Annotation>
<Annotation Id="37" Type="sentence" StartNode="98" EndNode="219">
<Feature>
  <Name className="java.lang.String">intensity</Name>
  <Value className="java.lang.String">medium</Value>
</Feature>
<Feature>
  <Name className="java.lang.String">sentence_id</Name>
  <Value className="java.lang.String">S2</Value>
</Feature>
<Feature>
  <Name className="java.lang.String">subjective/objective</Name>
  <Value className="java.lang.String">objective</Value>
</Feature>
<Feature>
  <Name className="java.lang.String">polarity</Name>
  <Value className="java.lang.String">neutral</Value>
</Feature>
</Annotation>
<Annotation Id="38" Type="sentence" StartNode="220" EndNode="332">
<Feature>
  <Name className="java.lang.String">intensity</Name>
  <Value className="java.lang.String">medium</Value>
</Feature>
<Feature>
  <Name className="java.lang.String">sentence_id</Name>
  <Value className="java.lang.String">S3</Value>
</Feature>
<Feature>
  <Name className="java.lang.String">subjective/objective</Name>
  <Value className="java.lang.String">objective</Value>
</Feature>
<Feature>
  <Name className="java.lang.String">polarity</Name>
  <Value className="java.lang.String">neutral</Value>
</Feature>
</Annotation>
<Annotation Id="39" Type="sentence" StartNode="333" EndNode="461">
<Feature>
  <Name className="java.lang.String">intensity</Name>
  <Value className="java.lang.String">medium</Value>
</Feature>
<Feature>
  <Name className="java.lang.String">sentence_id</Name>
  <Value className="java.lang.String">S4</Value>
</Feature>
<Feature>
  <Name className="java.lang.String">subjective/objective</Name>
  <Value className="java.lang.String">objective</Value>
</Feature>
<Feature>
  <Name className="java.lang.String">polarity</Name>
  <Value className="java.lang.String">neutral</Value>
</Feature>
</Annotation>
<Annotation Id="40" Type="sentence" StartNode="464" EndNode="633">
<Feature>
  <Name className="java.lang.String">intensity</Name>
  <Value className="java.lang.String">medium</Value>
</Feature>
<Feature>
  <Name className="java.lang.String">sentence_id</Name>
  <Value className="java.lang.String">S5</Value>
</Feature>
<Feature>
  <Name className="java.lang.String">subjective/objective</Name>
  <Value className="java.lang.String">objective</Value>
</Feature>
<Feature>
  <Name className="java.lang.String">polarity</Name>
  <Value className="java.lang.String">neutral</Value>
</Feature>
</Annotation>
<Annotation Id="41" Type="narrator" StartNode="637" EndNode="644">
<Feature>
  <Name className="java.lang.String">narrator_id</Name>
  <Value className="java.lang.String">N6_1</Value>
</Feature>
<Feature>
  <Name className="java.lang.String">sentence_id</Name>
  <Value className="java.lang.String">S6</Value>
</Feature>
</Annotation>
<Annotation Id="42" Type="sentence" StartNode="634" EndNode="756">
<Feature>
  <Name className="java.lang.String">intensity</Name>
  <Value className="java.lang.String">medium</Value>
</Feature>
<Feature>
  <Name className="java.lang.String">sentence_id</Name>
  <Value className="java.lang.String">S6</Value>
</Feature>
<Feature>
  <Name className="java.lang.String">subjective/objective</Name>
  <Value className="java.lang.String">objective</Value>
</Feature>
<Feature>
  <Name className="java.lang.String">polarity</Name>
  <Value className="java.lang.String">neutral</Value>
</Feature>
</Annotation>
</AnnotationSet>

<!-- Named annotation set -->

<AnnotationSet Name="Original markups">
<Annotation Id="0" Type="newsitem" StartNode="0" EndNode="2669">
<Feature>
  <Name className="java.lang.String">date</Name>
  <Value className="java.lang.String">1996-08-25</Value>
</Feature>
<Feature>
  <Name className="java.lang.String">itemid</Name>
  <Value className="java.lang.String">12872</Value>
</Feature>
<Feature>
  <Name className="java.lang.String">xml:lang</Name>
  <Value className="java.lang.String">en</Value>
</Feature>
<Feature>
  <Name className="java.lang.String">id</Name>
  <Value className="java.lang.String">root</Value>
</Feature>
</Annotation>
<Annotation Id="1" Type="title" StartNode="1" EndNode="41">
</Annotation>
<Annotation Id="2" Type="headline" StartNode="42" EndNode="78">
</Annotation>
<Annotation Id="3" Type="dateline" StartNode="79" EndNode="96">
</Annotation>
<Annotation Id="4" Type="text" StartNode="97" EndNode="2608">
</Annotation>
<Annotation Id="5" Type="p" StartNode="98" EndNode="219">
</Annotation>
<Annotation Id="6" Type="p" StartNode="220" EndNode="332">
</Annotation>
<Annotation Id="7" Type="p" StartNode="333" EndNode="463">
</Annotation>
<Annotation Id="8" Type="p" StartNode="464" EndNode="633">
</Annotation>
<Annotation Id="9" Type="p" StartNode="634" EndNode="758">
</Annotation>
<Annotation Id="10" Type="p" StartNode="759" EndNode="866">
</Annotation>
<Annotation Id="11" Type="p" StartNode="867" EndNode="1039">
</Annotation>
<Annotation Id="12" Type="p" StartNode="1040" EndNode="1216">
</Annotation>
<Annotation Id="13" Type="p" StartNode="1217" EndNode="1398">
</Annotation>
<Annotation Id="14" Type="p" StartNode="1399" EndNode="1693">
</Annotation>
<Annotation Id="15" Type="p" StartNode="1694" EndNode="1828">
</Annotation>
<Annotation Id="16" Type="p" StartNode="1829" EndNode="1953">
</Annotation>
<Annotation Id="17" Type="p" StartNode="1954" EndNode="2386">
</Annotation>
<Annotation Id="18" Type="p" StartNode="2387" EndNode="2570">
</Annotation>
<Annotation Id="19" Type="p" StartNode="2571" EndNode="2607">
</Annotation>
<Annotation Id="20" Type="copyright" StartNode="2609" EndNode="2633">
</Annotation>
<Annotation Id="21" Type="metadata" StartNode="2634" EndNode="2668">
</Annotation>
<Annotation Id="22" Type="codes" StartNode="2635" EndNode="2647">
<Feature>
  <Name className="java.lang.String">class</Name>
  <Value className="java.lang.String">bip:countries:1.0</Value>
</Feature>
</Annotation>
<Annotation Id="23" Type="code" StartNode="2638" EndNode="2646">
<Feature>
  <Name className="java.lang.String">code</Name>
  <Value className="java.lang.String">UK</Value>
</Feature>
</Annotation>
<Annotation Id="24" Type="editdetail" StartNode="2643" EndNode="2643">
<Feature>
  <Name className="java.lang.String">attribution</Name>
  <Value className="java.lang.String">Reuters BIP Coding Group</Value>
</Feature>
<Feature>
  <Name className="java.lang.String">date</Name>
  <Value className="java.lang.String">1996-08-25</Value>
</Feature>
<Feature>
  <Name className="java.lang.String">action</Name>
  <Value className="java.lang.String">confirmed</Value>
</Feature>
<Feature>
  <Name className="java.lang.String">isEmptyAndSpan</Name>
  <Value className="java.lang.String">true</Value>
</Feature>
</Annotation>
<Annotation Id="25" Type="codes" StartNode="2648" EndNode="2660">
<Feature>
  <Name className="java.lang.String">class</Name>
  <Value className="java.lang.String">bip:topics:1.0</Value>
</Feature>
</Annotation>
<Annotation Id="26" Type="code" StartNode="2651" EndNode="2659">
<Feature>
  <Name className="java.lang.String">code</Name>
  <Value className="java.lang.String">C33</Value>
</Feature>
</Annotation>
<Annotation Id="27" Type="editdetail" StartNode="2656" EndNode="2656">
<Feature>
  <Name className="java.lang.String">attribution</Name>
  <Value className="java.lang.String">Reuters BIP Coding Group</Value>
</Feature>
<Feature>
  <Name className="java.lang.String">date</Name>
  <Value className="java.lang.String">1996-08-25</Value>
</Feature>
<Feature>
  <Name className="java.lang.String">action</Name>
  <Value className="java.lang.String">confirmed</Value>
</Feature>
<Feature>
  <Name className="java.lang.String">isEmptyAndSpan</Name>
  <Value className="java.lang.String">true</Value>
</Feature>
</Annotation>
<Annotation Id="28" Type="dc" StartNode="2661" EndNode="2661">
<Feature>
  <Name className="java.lang.String">isEmptyAndSpan</Name>
  <Value className="java.lang.String">true</Value>
</Feature>
<Feature>
  <Name className="java.lang.String">value</Name>
  <Value className="java.lang.String">1996-08-25</Value>
</Feature>
<Feature>
  <Name className="java.lang.String">element</Name>
  <Value className="java.lang.String">dc.date.created</Value>
</Feature>
</Annotation>
<Annotation Id="29" Type="dc" StartNode="2662" EndNode="2662">
<Feature>
  <Name className="java.lang.String">isEmptyAndSpan</Name>
  <Value className="java.lang.String">true</Value>
</Feature>
<Feature>
  <Name className="java.lang.String">value</Name>
  <Value className="java.lang.String">Reuters Holdings Plc</Value>
</Feature>
<Feature>
  <Name className="java.lang.String">element</Name>
  <Value className="java.lang.String">dc.publisher</Value>
</Feature>
</Annotation>
<Annotation Id="30" Type="dc" StartNode="2663" EndNode="2663">
<Feature>
  <Name className="java.lang.String">isEmptyAndSpan</Name>
  <Value className="java.lang.String">true</Value>
</Feature>
<Feature>
  <Name className="java.lang.String">value</Name>
  <Value className="java.lang.String">1996-08-25</Value>
</Feature>
<Feature>
  <Name className="java.lang.String">element</Name>
  <Value className="java.lang.String">dc.date.published</Value>
</Feature>
</Annotation>
<Annotation Id="31" Type="dc" StartNode="2664" EndNode="2664">
<Feature>
  <Name className="java.lang.String">isEmptyAndSpan</Name>
  <Value className="java.lang.String">true</Value>
</Feature>
<Feature>
  <Name className="java.lang.String">value</Name>
  <Value className="java.lang.String">Reuters</Value>
</Feature>
<Feature>
  <Name className="java.lang.String">element</Name>
  <Value className="java.lang.String">dc.source</Value>
</Feature>
</Annotation>
<Annotation Id="32" Type="dc" StartNode="2665" EndNode="2665">
<Feature>
  <Name className="java.lang.String">isEmptyAndSpan</Name>
  <Value className="java.lang.String">true</Value>
</Feature>
<Feature>
  <Name className="java.lang.String">value</Name>
  <Value className="java.lang.String">LONDON</Value>
</Feature>
<Feature>
  <Name className="java.lang.String">element</Name>
  <Value className="java.lang.String">dc.creator.location</Value>
</Feature>
</Annotation>
<Annotation Id="33" Type="dc" StartNode="2666" EndNode="2666">
<Feature>
  <Name className="java.lang.String">isEmptyAndSpan</Name>
  <Value className="java.lang.String">true</Value>
</Feature>
<Feature>
  <Name className="java.lang.String">value</Name>
  <Value className="java.lang.String">UK</Value>
</Feature>
<Feature>
  <Name className="java.lang.String">element</Name>
  <Value className="java.lang.String">dc.creator.location.country.name</Value>
</Feature>
</Annotation>
<Annotation Id="34" Type="dc" StartNode="2667" EndNode="2667">
<Feature>
  <Name className="java.lang.String">isEmptyAndSpan</Name>
  <Value className="java.lang.String">true</Value>
</Feature>
<Feature>
  <Name className="java.lang.String">value</Name>
  <Value className="java.lang.String">Reuters</Value>
</Feature>
<Feature>
  <Name className="java.lang.String">element</Name>
  <Value className="java.lang.String">dc.source</Value>
</Feature>
</Annotation>
</AnnotationSet>

</GateDocument>
